macaddress.py
macaddress-2.0.1.dist-info/LICENSE
macaddress-2.0.1.dist-info/METADATA
macaddress-2.0.1.dist-info/WHEEL
macaddress-2.0.1.dist-info/top_level.txt
macaddress-2.0.1.dist-info/RECORD
