Metadata-Version: 2.1
Name: macaddress
Version: 2.0.1
Summary: Like ``ipaddress``, but for hardware identifiers such as MAC addresses.
Home-page: https://github.com/mentalisttraceur/python-macaddress
Author: Alexander Kozhevnikov
Author-email: mentalisttraceur@gmail.com
License: 0BSD
Platform: UNKNOWN
Classifier: Development Status :: 5 - Production/Stable
Classifier: Programming Language :: Python :: 3
Classifier: Operating System :: OS Independent
License-File: LICENSE
